derive_action_signing/__init__.py
derive_action_signing/module_data/__init__.py
derive_action_signing/module_data/create_subaccount.py
derive_action_signing/module_data/deposit.py
derive_action_signing/module_data/module_data.py
derive_action_signing/module_data/rfq.py
derive_action_signing/module_data/trade.py
derive_action_signing/module_data/transfer_erc20.py
derive_action_signing/module_data/transfer_position.py
derive_action_signing/module_data/transfer_positions.py
derive_action_signing/module_data/withdraw.py
derive_action_signing/signed_action.py
derive_action_signing/utils.py
derive_action_signing-0.0.13.dist-info/METADATA
derive_action_signing-0.0.13.dist-info/WHEEL
derive_action_signing-0.0.13.dist-info/RECORD
