Metadata-Version: 2.3
Name: derive_action_signing
Version: 0.0.13
Summary: Python package to sign on-chain self-custodial requests for orders, transfers, deposits, withdrawals and RFQs.
Author: Derive.xyz
Author-email: joshua@derive.xyz
Requires-Python: >=3.9,<4.0
Classifier: License :: OSI Approved :: MIT License
Classifier: Operating System :: OS Independent
Classifier: Programming Language :: Python :: 3
Classifier: Programming Language :: Python :: 3.9
Classifier: Programming Language :: Python :: 3.10
Classifier: Programming Language :: Python :: 3.11
Classifier: Programming Language :: Python :: 3.12
Classifier: Programming Language :: Python :: 3.13
Requires-Dist: eth-abi (>=4.2.1)
Requires-Dist: eth-account (>=0.13.4)
Requires-Dist: eth-typing (>=4,<6)
Requires-Dist: hexbytes (>=0.3.1)
Requires-Dist: setuptools (>=75.8.0,<76.0.0)
Requires-Dist: web3 (>=6.4.0,<8.0.0)
Project-URL: Homepage, https://github.com/derivexyz/v2-action-signing-python
Project-URL: Repository, https://github.com/derivexyz/v2-action-signing-python
